reddash/LICENSE.md
reddash/__init__.py
reddash/__main__.py
reddash/app/__init__.py
reddash/app/constants.py
reddash/app/tasks.py
reddash/app/utils.py
reddash/app/api/__init__.py
reddash/app/api/routes.py
reddash/app/base/__init__.py
reddash/app/base/routes.py
reddash/app/base/static/assets/css/black-dashboard.css
reddash/app/base/static/assets/css/black-dashboard.css.map
reddash/app/base/static/assets/css/black-dashboard.min.css
reddash/app/base/static/assets/css/bootstrap-select.min.css
reddash/app/base/static/assets/css/nucleo-icons.css
reddash/app/base/static/assets/fonts/nucleo.eot
reddash/app/base/static/assets/fonts/nucleo.ttf
reddash/app/base/static/assets/fonts/nucleo.woff
reddash/app/base/static/assets/fonts/nucleo.woff2
reddash/app/base/static/assets/img/dnd.png
reddash/app/base/static/assets/img/idle.png
reddash/app/base/static/assets/img/offline.png
reddash/app/base/static/assets/img/online.png
reddash/app/base/static/assets/js/black-dashboard.js
reddash/app/base/static/assets/js/black-dashboard.js.map
reddash/app/base/static/assets/js/black-dashboard.min.js
reddash/app/base/static/assets/js/bootstrap-select.min.js
reddash/app/base/static/assets/js/core/bootstrap.min.js
reddash/app/base/static/assets/js/core/jquery.min.js
reddash/app/base/static/assets/js/core/popper.min.js
reddash/app/base/static/assets/js/plugins/bootstrap-notify.js
reddash/app/base/static/assets/js/plugins/chartjs.min.js
reddash/app/base/static/assets/js/plugins/perfect-scrollbar.jquery.min.js
reddash/app/base/static/assets/scss/black-dashboard.scss
reddash/app/base/static/assets/scss/black-dashboard/_buttons.scss
reddash/app/base/static/assets/scss/black-dashboard/_typography.scss
reddash/app/base/static/assets/scss/black-dashboard/bootstrap/_alert.scss
reddash/app/base/static/assets/scss/black-dashboard/bootstrap/_badge.scss
reddash/app/base/static/assets/scss/black-dashboard/bootstrap/_breadcrumb.scss
reddash/app/base/static/assets/scss/black-dashboard/bootstrap/_button-group.scss
Red_Dashboard-0.1.8a0.dist-info/LICENSE
Red_Dashboard-0.1.8a0.dist-info/METADATA
Red_Dashboard-0.1.8a0.dist-info/WHEEL
Red_Dashboard-0.1.8a0.dist-info/entry_points.txt
Red_Dashboard-0.1.8a0.dist-info/top_level.txt
Red_Dashboard-0.1.8a0.dist-info/RECORD
