Metadata-Version: 2.1
Name: Red-Dashboard
Version: 0.1.8a0
Summary: An easy-to-use interactive web dashboard to control your Redbot.
Home-page: https://github.com/Cog-Creators/Red-Dashboard
Author: Neuro Assassin
Author-email: redbotdashboard@gmail.com
License: AGPL-3.0
Project-URL: Third Party Discord Server, https://discord.gg/vQZTdB9
Project-URL: Documentation, https://red-dashboard.readthedocs.io/en/latest/
Project-URL: Donate on Patreon, https://www.patreon.com/neuroassassin
Project-URL: Source Code, https://github.com/NeuroAssassin/Red-Dashboard
Project-URL: Red Source Code, https://github.com/Cog-Creators/Red-DiscordBot
Project-URL: Red Discord Server, https://discord.gg/red
Platform: UNKNOWN
Classifier: Development Status :: 3 - Alpha
Classifier: Framework :: Flask
Classifier: Intended Audience :: Developers
Classifier: Intended Audience :: End Users/Desktop
Classifier: License :: OSI Approved :: GNU Affero General Public License v3
Classifier: Natural Language :: English
Classifier: Operating System :: MacOS :: MacOS X
Classifier: Operating System :: Microsoft :: Windows
Classifier: Operating System :: POSIX :: Linux
Classifier: Programming Language :: Python :: 3.8
Classifier: Topic :: Internet :: WWW/HTTP :: Dynamic Content :: Content Management System
Requires-Python: <3.9,>=3.8.1
Requires-Dist: flask (==1.1.2)
Requires-Dist: requests (==2.23.0)
Requires-Dist: cryptography (==3.2)
Requires-Dist: websocket-client (==0.57.0)
Requires-Dist: waitress (==1.4.3)
Requires-Dist: rich (==1.3.1)
Requires-Dist: fuzzywuzzy (==0.18.0)
Requires-Dist: python-Levenshtein (==0.12.0)
Requires-Dist: pyjwt (==1.7.1)
Requires-Dist: flask-babel (==1.0.0)
Provides-Extra: docs
Requires-Dist: Sphinx (==2.4.4) ; extra == 'docs'
Requires-Dist: sphinx-rtd-theme (==0.4.3) ; extra == 'docs'
Provides-Extra: style
Requires-Dist: black (==19.10b0) ; extra == 'style'
